commonutil_sanitize/__init__.py
commonutil_sanitize/py.typed
commonutil_sanitize-3.0.1.dist-info/METADATA
commonutil_sanitize-3.0.1.dist-info/WHEEL
commonutil_sanitize-3.0.1.dist-info/top_level.txt
commonutil_sanitize-3.0.1.dist-info/RECORD
