Metadata-Version: 2.1
Name: commonutil-sanitize
Version: 3.0.1
Summary: Routines support text sanitization
Classifier: Development Status :: 5 - Production/Stable
Classifier: Intended Audience :: Developers
Classifier: License :: OSI Approved :: MIT License
Classifier: Operating System :: POSIX
Requires-Python: >=3.7
